setup.py
giganews/__init__.py
giganews/giganews.py
giganews/logging.py
giganews/utils.py
giganews.egg-info/PKG-INFO
giganews.egg-info/SOURCES.txt
giganews.egg-info/dependency_links.txt
giganews.egg-info/requires.txt
giganews.egg-info/top_level.txt