Metadata-Version: 1.0
Name: giganews
Version: 0.0.1
Summary: A python interface to giganews
Home-page: https://github.com/jjjake/giganews
Author: Jacob M. Johnson
Author-email: jake@archive.org
License: LICENSE
Platform: UNKNOWN
